rbf_lang/__init__.py
rbf_lang/__main__.py
rbf_lang/cli.py
rbf_lang/command.py
rbf_lang/exceptions.py
rbf_lang/program.py
rbf_lang/py.typed
rbf_lang/reverse.py
rbf_lang/runner.py
rbf_lang/tape.py
rbf_lang-0.2.2.dist-info/entry_points.txt
rbf_lang-0.2.2.dist-info/licenses/LICENSE
rbf_lang-0.2.2.dist-info/WHEEL
rbf_lang-0.2.2.dist-info/METADATA
rbf_lang-0.2.2.dist-info/RECORD
