Metadata-Version: 2.4
Name: rbf-lang
Version: 0.2.2
Summary: Reversible BitFuck (RBF) interpreter
Keywords: esolang,reversible,turing tarpits,interpreter
Author-email: Marcin Konowalczyk <marcin.konow@lczyk.xyz>
Requires-Python: >=3.9
Classifier: Programming Language :: Python :: 3
Classifier: License :: OSI Approved :: MIT License
Classifier: Operating System :: OS Independent
Classifier: Topic :: Software Development :: Interpreters
Classifier: Intended Audience :: Developers
Classifier: Typing :: Typed
License-File: LICENSE
Project-URL: home, https://github.com/marcinkonowalczyk/rbf-lang
